sharehound/__main__.py
sharehound/__version__.py
sharehound/collector/__init__.py
sharehound/collector/collect_contents_at_depth.py
sharehound/collector/collect_contents_in_share.py
sharehound/collector/collect_ntfs_rights.py
sharehound/collector/collect_share_rights.py
sharehound/collector/collect_shares.py
sharehound/collector/opengraph_context.py
sharehound/core/Config.py
sharehound/core/Credentials.py
sharehound/core/Logger.py
sharehound/core/MicrosoftDNS.py
sharehound/core/SIDResolver.py
sharehound/core/SMBSession.py
sharehound/core/__init__.py
sharehound/kinds.py
sharehound/status.py
sharehound/targets.py
sharehound/tests/run_tests.py
sharehound/utils/__init__.py
sharehound/utils/delta_time.py
sharehound/utils/utils.py
sharehound/worker.py
sharehound-1.0.1.dist-info/METADATA
sharehound-1.0.1.dist-info/WHEEL
sharehound-1.0.1.dist-info/entry_points.txt
sharehound-1.0.1.dist-info/RECORD
