Metadata-Version: 2.4
Name: sharehound
Version: 1.0.1
Summary: A Python script to generate a bloodhound opengraph of the rights of shares on a remote Windows machine.
License: MIT
Author: p0dalirius
Requires-Python: >=3.11
Classifier: License :: OSI Approved :: MIT License
Classifier: Programming Language :: Python :: 3
Classifier: Programming Language :: Python :: 3.11
Classifier: Programming Language :: Python :: 3.12
Classifier: Programming Language :: Python :: 3.13
Classifier: Programming Language :: Python :: 3.14
Requires-Dist: argcomplete
Requires-Dist: bhopengraph (>=1.1.0)
Requires-Dist: impacket (>=0.10.0)
Requires-Dist: lark
Requires-Dist: pycryptodome (>=3.23.0)
Requires-Dist: rich
Requires-Dist: sectools (>=1.5.1)
Requires-Dist: shareql
